SailsJsGuanfangWendang/README.md
SailsJsGuanfangWendang/__init__.py
SailsJsGuanfangWendang/__main__.py
SailsJsGuanfangWendang/file.epub
SailsJsGuanfangWendang/index.html
SailsJsGuanfangWendang/css/__init__.py
SailsJsGuanfangWendang/css/annotations.css
SailsJsGuanfangWendang/css/main.css
SailsJsGuanfangWendang/css/normalize.css
SailsJsGuanfangWendang/css/popup.css
SailsJsGuanfangWendang/font/__init__.py
SailsJsGuanfangWendang/font/fontello.eot
SailsJsGuanfangWendang/font/fontello.svg
SailsJsGuanfangWendang/font/fontello.ttf
SailsJsGuanfangWendang/font/fontello.woff
SailsJsGuanfangWendang/img/__init__.py
SailsJsGuanfangWendang/img/annotator-glyph-sprite.png
SailsJsGuanfangWendang/img/annotator-icon-sprite.png
SailsJsGuanfangWendang/img/apple-touch-icon.png
SailsJsGuanfangWendang/img/cancelfullscreen.png
SailsJsGuanfangWendang/img/close.png
SailsJsGuanfangWendang/img/fullscreen.png
SailsJsGuanfangWendang/img/loader.gif
SailsJsGuanfangWendang/img/menu-icon.png
SailsJsGuanfangWendang/img/save.png
SailsJsGuanfangWendang/img/saved.png
SailsJsGuanfangWendang/img/settings-s.png
SailsJsGuanfangWendang/img/settings.png
SailsJsGuanfangWendang/img/star.png
SailsJsGuanfangWendang/js/__init__.py
SailsJsGuanfangWendang/js/epub.js
SailsJsGuanfangWendang/js/epub.min.js
SailsJsGuanfangWendang/js/epub.min.map
SailsJsGuanfangWendang/js/hooks.min.js
SailsJsGuanfangWendang/js/hooks.min.map
SailsJsGuanfangWendang/js/reader.js
SailsJsGuanfangWendang/js/reader.js.map
SailsJsGuanfangWendang/js/reader.min.js
SailsJsGuanfangWendang/js/reader.min.map
SailsJsGuanfangWendang/js/hooks/__init__.py
SailsJsGuanfangWendang/js/hooks/extensions/__init__.py
SailsJsGuanfangWendang/js/hooks/extensions/highlight.js
SailsJsGuanfangWendang/js/libs/__init__.py
SailsJsGuanfangWendang/js/libs/jquery.min.js
SailsJsGuanfangWendang/js/libs/localforage.min.js
SailsJsGuanfangWendang/js/libs/screenfull.js
SailsJsGuanfangWendang/js/libs/screenfull.min.js
SailsJsGuanfangWendang/js/libs/zip.min.js
sails_js_guanfang_wendang-2024.3.1.0.dist-info/METADATA
sails_js_guanfang_wendang-2024.3.1.0.dist-info/WHEEL
sails_js_guanfang_wendang-2024.3.1.0.dist-info/entry_points.txt
sails_js_guanfang_wendang-2024.3.1.0.dist-info/top_level.txt
sails_js_guanfang_wendang-2024.3.1.0.dist-info/RECORD
